message_push/__init__.py
message_push/anpush_sender.py
message_push/async_sender.py
message_push/bark_sender.py
message_push/config_loader.py
message_push/dingtalk_sender.py
message_push/discord_sender.py
message_push/email_sender.py
message_push/feishu_sender.py
message_push/igot_sender.py
message_push/pushplus_sender.py
message_push/sender.py
message_push/telegram_sender.py
message_push/wechat_sender.py
message_push/whatsapp_sender.py
tests/__init__.py
tests/test_senders.py
MessagePush-0.0.2.dist-info/LICENSE
MessagePush-0.0.2.dist-info/METADATA
MessagePush-0.0.2.dist-info/WHEEL
MessagePush-0.0.2.dist-info/top_level.txt
MessagePush-0.0.2.dist-info/RECORD
