Metadata-Version: 2.1
Name: MessagePush
Version: 0.0.2
Summary: A Python package for sending messages via various platforms asynchronously.
Home-page: https://github.com/yourusername/MessagePush
Author: XiaoqiangClub
Author-email: xiaoqiangclub@hotmail.com
Classifier: Programming Language :: Python :: 3
Classifier: License :: OSI Approved :: MIT License
Classifier: Operating System :: OS Independent
Requires-Python: >=3.6
License-File: LICENSE
Requires-Dist: httpx
Requires-Dist: pyyaml
